arcana_codex/__init__.py
arcana_codex/_internals.py
arcana_codex/_utils.py
arcana_codex/async_client.py
arcana_codex/client.py
arcana_codex/exceptions.py
arcana_codex/models.py
arcana_codex-0.2.0.dist-info/METADATA
arcana_codex-0.2.0.dist-info/WHEEL
arcana_codex-0.2.0.dist-info/licenses/LICENSE.md
arcana_codex-0.2.0.dist-info/RECORD
