Metadata-Version: 2.4
Name: arcana-codex
Version: 0.2.0
Summary: Python SDK for Arcana
Project-URL: homepage, http://arcana.ad/
Project-URL: repository, https://github.com/arcana-ad/arcana-codex
Project-URL: documentation, https://github.com/arcana-ad/arcana-codex
Author-email: Saurabh Ghanekar <ghanekarsaurabh8@gmail.com>
License-Expression: Apache-2.0
License-File: LICENSE.md
Requires-Python: >=3.10
Requires-Dist: httpx>=0.28
Requires-Dist: pydantic>=2.10
